CHANGELOG.md
docs/CHANGELOG.md
torch_to_nnef/__init__.py
torch_to_nnef/_optional_types.py
torch_to_nnef/collect_env.py
torch_to_nnef/compress.py
torch_to_nnef/console.py
torch_to_nnef/dtypes.py
torch_to_nnef/exceptions.py
torch_to_nnef/export.py
torch_to_nnef/log.py
torch_to_nnef/model_wrapper.py
torch_to_nnef/nemo_tract.py
torch_to_nnef/nnef_graph.py
torch_to_nnef/utils.py
torch_to_nnef/inference_target/__init__.py
torch_to_nnef/inference_target/base.py
torch_to_nnef/inference_target/khronos.py
torch_to_nnef/inference_target/tract.py
torch_to_nnef/llm_tract/__init__.py
torch_to_nnef/llm_tract/cli.py
torch_to_nnef/llm_tract/config.py
torch_to_nnef/llm_tract/exporter.py
torch_to_nnef/llm_tract/models/__init__.py
torch_to_nnef/llm_tract/models/base.py
torch_to_nnef/nnef_io/tensor.py
torch_to_nnef/nnef_io/writer.py
torch_to_nnef/op/__init__.py
torch_to_nnef/op/helper.py
torch_to_nnef/op/quantized.py
torch_to_nnef/op/aten/__init__.py
torch_to_nnef/op/aten/activation.py
torch_to_nnef/op/aten/attn.py
torch_to_nnef/op/aten/axes_change.py
torch_to_nnef/op/aten/complex.py
torch_to_nnef/op/aten/concat.py
torch_to_nnef/op/aten/expand.py
torch_to_nnef/op/aten/fft.py
torch_to_nnef/op/aten/math.py
torch_to_nnef/op/aten/matmul.py
torch_to_nnef/op/aten/norm.py
torch_to_nnef/op/aten/other.py
torch_to_nnef/op/aten/pad.py
torch_to_nnef/op/aten/pool.py
torch_to_nnef/op/aten/qops.py
torch_to_nnef/op/aten/reducer.py
torch_to_nnef/op/aten/selector.py
torch_to_nnef/op/aten/split.py
torch_to_nnef/op/aten/tensor_build.py
torch_to_nnef/op/aten/unary.py
torch_to_nnef/op/custom_extractors/__init__.py
torch_to_nnef/op/custom_extractors/base.py
torch_to_nnef/op/custom_extractors/rnn.py
torch_to_nnef/op/fragment/__init__.py
torch_to_nnef/op/fragment/addmm.nnef
torch_to_nnef/op/fragment/atan2.nnef
torch_to_nnef/op/fragment/dyn_slice.nnef
torch_to_nnef/op/fragment/dyn_slice_begin.nnef
torch_to_nnef/op/fragment/erf.nnef
torch_to_nnef/op/fragment/expm1.nnef
torch_to_nnef/op/fragment/fmod.nnef
torch_to_nnef-0.20.3.dist-info/METADATA
torch_to_nnef-0.20.3.dist-info/WHEEL
torch_to_nnef-0.20.3.dist-info/entry_points.txt
torch_to_nnef-0.20.3.dist-info/licenses/LICENSE
torch_to_nnef-0.20.3.dist-info/RECORD
