Metadata-Version: 2.4
Name: torch_to_nnef
Version: 0.20.3
Summary: Any PyTorch Model to NNEF file format.
Project-URL: Homepage, https://github.com/sonos/torch-to-nnef
Author-email: Julien Balian <julien.balian@sonos.com>
License-Expression: MIT AND Apache-2.0
License-File: LICENSE
Keywords: ai,deep learning,exchange format,export,llm,machine learning,nnef,pytorch,torch,transformers
Classifier: Development Status :: 4 - Beta
Classifier: Intended Audience :: Developers
Classifier: Natural Language :: English
Classifier: Programming Language :: Python :: 3
Classifier: Programming Language :: Python :: 3.9
Classifier: Programming Language :: Python :: 3.10
Classifier: Programming Language :: Python :: 3.11
Classifier: Programming Language :: Python :: 3.12
Classifier: Programming Language :: Python :: 3.13
Requires-Dist: mako<2.0,>=1.0.0
Requires-Dist: nnef-tools<2,>=1.0.7
Requires-Dist: nnef<2,>=1.0.7
Requires-Dist: numpy<3,>=1.26.0
Requires-Dist: torch<3,>=1.8.0
Requires-Dist: typing-extensions>=4.0.0
Provides-Extra: llm-tract
Requires-Dist: huggingface-hub>0.24; extra == 'llm-tract'
Requires-Dist: protobuf>5; extra == 'llm-tract'
Requires-Dist: sentencepiece<0.3,>=0.2.0; extra == 'llm-tract'
Requires-Dist: tokenizers>=0.13.3; extra == 'llm-tract'
Requires-Dist: transformers<5,>=4.35.2; extra == 'llm-tract'
Provides-Extra: llm-tract-accelerate
Requires-Dist: accelerate; extra == 'llm-tract-accelerate'
Provides-Extra: nemo-tract
Requires-Dist: nemo-toolkit[asr]<2.7.0,>=2.0.0; extra == 'nemo-tract'
Provides-Extra: peft
Requires-Dist: peft; extra == 'peft'
Provides-Extra: safetensors
Requires-Dist: safetensors; extra == 'safetensors'
Provides-Extra: test
Requires-Dist: coverage[toml]; extra == 'test'
Requires-Dist: librosa==0.11.0; extra == 'test'
Requires-Dist: mypy~=1.13; extra == 'test'
Requires-Dist: prospector; extra == 'test'
Requires-Dist: pytest-cov<7,>=6.0.0; extra == 'test'
Requires-Dist: pytest<9,>=8.3.3; extra == 'test'
Requires-Dist: ruff<1.0; extra == 'test'
Requires-Dist: sentencepiece<0.3,>=0.2.0; extra == 'test'
Requires-Dist: tokenizers>=0.13.3; extra == 'test'
Requires-Dist: torchaudio<3,>=0.9.0; extra == 'test'
Requires-Dist: torchvision<0.25,>=0.10.0; extra == 'test'
Requires-Dist: transformers<5,>=4.35.2; extra == 'test'
